Workbook

Sheet 0. Módulos Sistema
A1: FICHA TÉCNICA – MÓDULOS DEL SISTEMA | SIGTRM – La Caqueteña
A2: Proyecto: Sistema Inteligente de Gestión para Taller de Reparación de Muebles | Fecha: Junio 2026
A3: Código | B3: Módulo | C3: Descripción | D3: Funciones Principales | E3: Usuarios con Acceso | F3: Prioridad
A4: GU | B4: Gestión de Usuarios | C4: Administración de perfiles, roles y seguridad. | D4: Crear/editar/eliminar usuarios · Asignar roles · Bloqueo por intentos fallidos · Bitácora | E4: Rep. Legal, Administrador | F4: Alta
A5: MUE | B5: Registro de Muebles | C5: Registro digital de muebles entrantes con categorización. | D5: Registro con fotos · Categorización · Vinculación a cliente y orden | E5: Administrador, Reparador | F5: Alta
A6: INV | B6: Control de Inventario | C6: Catálogo digital de materiales e insumos. | D6: Registro de insumos · Descuento automático · Alertas de stock bajo | E6: Administrador, Logística | F6: Alta
A7: NOT | B7: Notificaciones | C7: Sistema de alertas internas y notificaciones al cliente. | D7: Correo automático al cliente · Alertas por demora · Integración SendGrid | E7: Todos los roles | F7: Media
A8: REP | B8: Reportes y Analítica | C8: Generación de informes operativos y tablero KPI. | D8: Tablero con muebles activos · Tiempo prom. de reparación · Exportación PDF/Excel | E8: Rep. Legal, Administrador | F8: Media
A9: CLI | B9: Gestión de Clientes | C9: Registro y consulta de clientes con historial. | D9: Crear/editar clientes · Historial de muebles · Búsqueda rápida | E9: Administrador | F9: Alta
A10: ORD | B10: Órdenes de Trabajo | C10: Seguimiento de 6 etapas del proceso productivo. | D10: Crear orden · Trazabilidad Recepción→Diagnóstico→Reparación→Inspección→Listo→Entregado · Tiempos | E10: Administrador, Reparador | F10: Alta

Sheet 1. Hardware
A1: FICHA TÉCNICA – HARDWARE | SIGTRM – La Caqueteña
A2: Aprendices SENA – Tecnólogo Desarrollo de Software | Fecha: Junio 2026
A3: # | B3: Componente | C3: Descripción / Especificación | D3: Cantidad | E3: Costo Unit. (COP) | F3: Costo Total (COP) | G3: Tipo | H3: Notas | I3: Enlace Ktronix
A4: A. Equipos de Desarrollo (3 aprendices – 3 portátiles)
A5: 1 | B5: Laptop Lenovo IdeaPad 3 | C5: AMD Ryzen 5 / 8 GB RAM / SSD 512 GB – uso desarrollo web y bases de datos | D5: 3 | E5: 1849900 | F5: =D5*E5 -> 5549700 | G5: CAPEX | H5: Costo único – adquisición | I5: https://www.ktronix.com/computadores-tablet/computadores-portatiles/c/BI_104_KTRON
A6: 2 | B6: Mouse inalámbrico | C6: Periférico USB inalámbrico – uno por aprendiz | D6: 3 | E6: 55000 | F6: =D6*E6 -> 165000 | G6: CAPEX | H6: Costo único – adquisición | I6: https://www.ktronix.com/accesorios-electronica/accesorios-computadores/perifericos/c/BI_0190_KTRON
A7: 3 | B7: Maletín / Morral portátil | C7: Protección para cada portátil | D7: 3 | E7: 65000 | F7: =D7*E7 -> 195000 | G7: CAPEX | H7: Costo único – adquisición | I7: https://www.ktronix.com/accesorios-electronica/accesorios-computadores/maletines-morrales-fundas/c/BI_0130_KTRON
A8: SUBTOTAL – Equipos de Desarrollo | F8: =SUM(F5:F7) -> 5909700
A9: B. Infraestructura de Red – Taller (arquitectura cloud – sin servidor local)
A10: 1 | B10: Router WiFi 5 TP-Link | C10: Doble banda – cubre área del taller | D10: 1 | E10: 159900 | F10: =D10*E10 -> 159900 | G10: CAPEX | H10: Costo único – adquisición | I10: https://www.ktronix.com/casa-inteligente-domotica/redes-wifi/c/BI_142_KTRON
A11: 2 | B11: Switch 8 puertos | C11: Fast Ethernet – cableado interno taller | D11: 1 | E11: 79000 | F11: =D11*E11 -> 79000 | G11: CAPEX | H11: Costo único – adquisición | I11: https://www.ktronix.com/casa-inteligente-domotica/redes-wifi/switches-red/c/BI_5006_KTRON
A12: 3 | B12: Cable UTP Cat 5e | C12: Rollo 50 m + accesorios RJ45 | D12: 1 | E12: 55000 | F12: =D12*E12 -> 55000 | G12: CAPEX | H12: Costo único – adquisición | I12: https://www.ktronix.com/accesorios-electronica/c/BI_AELE_KTRON
A13: 4 | B13: UPS 600 VA | C13: Protección eléctrica para equipos del taller | D13: 1 | E13: 189000 | F13: =D13*E13 -> 189000 | G13: CAPEX | H13: Costo único – adquisición | I13: https://www.ktronix.com/accesorios-electronica/reguladores-voltaje-ups-multitomas/c/BI_146_KTRON
A14: SUBTOTAL – Infraestructura Red Taller | F14: =SUM(F10:F13) -> 482900
A15: TOTAL HARDWARE | F15: =F8+F14 -> 6392600
A16: Fuente precios: Ktronix.com – Junio 2026 | Precios sujetos a variación.

Sheet 2. Software
A1: FICHA TÉCNICA – SOFTWARE Y LICENCIAS | SIGTRM – La Caqueteña
A2: Herramientas conocidas por aprendices SENA – Junio 2026
A3: # | B3: Software / Servicio | C3: Descripción | D3: Tipo Costo | E3: Costo/mes (COP) | F3: Meses | G3: Costo Total (COP)
A4: A. Herramientas de Desarrollo – Open Source / Gratuito
A5: 1 | B5: NetBeans IDE | C5: IDE principal para desarrollo Java. Open source – Apache. | D5: Gratis | E5: 0 | F5: 18 | G5: =E5*F5 -> 0
A6: 2 | B6: Visual Studio Code | C6: Editor de código liviano. Open source – Microsoft. | D6: Gratis | E6: 0 | F6: 18 | G6: =E6*F6 -> 0
A7: 3 | B7: MySQL Community | C7: Motor de base de datos relacional. Gratuito – Oracle. | D7: Gratis | E7: 0 | F7: 18 | G7: =E7*F7 -> 0
A8: 4 | B8: MySQL Workbench | C8: Herramienta visual de administración de MySQL. Gratuita. | D8: Gratis | E8: 0 | F8: 18 | G8: =E8*F8 -> 0
A9: 5 | B9: Git + GitHub Free | C9: Control de versiones + repo privado (plan gratuito). | D9: Gratis | E9: 0 | F9: 18 | G9: =E9*F9 -> 0
A10: 6 | B10: Visual Paradigm CE | C10: Modelado UML, diagramas ER y de casos de uso. Ed. Community. | D10: Gratis | E10: 0 | F10: 18 | G10: =E10*F10 -> 0
A11: 7 | B11: Postman Free | C11: Pruebas y documentación de API REST. | D11: Gratis | E11: 0 | F11: 18 | G11: =E11*F11 -> 0
A12: 8 | B12: Figma Free | C12: Diseño mockups UI/UX – hasta 3 proyectos. | D12: Gratis | E12: 0 | F12: 18 | G12: =E12*F12 -> 0
A13: 9 | B13: Draw.io / Diagrams.net | C13: Diagramas de arquitectura, BD y flujos. 100% gratuito. | D13: Gratis | E13: 0 | F13: 18 | G13: =E13*F13 -> 0
A14: 10 | B14: Trello Free | C14: Gestión ágil de tareas del equipo. | D14: Gratis | E14: 0 | F14: 18 | G14: =E14*F14 -> 0
A15: 11 | B15: XAMPP | C15: Servidor local Apache + MySQL + PHP para pruebas. | D15: Gratis | E15: 0 | F15: 18 | G15: =E15*F15 -> 0
A16: SUBTOTAL – Stack Open Source / Gratuito | G16: =SUM(G5:G15) -> 0
A17: B. Servicios en la Nube – Despliegue y Operación (18 meses)
A18: 1 | B18: Railway (hosting backend) | C18: Plan Starter gratuito – 500 h/mes + 1 GB RAM. Suficiente para proyecto SENA. | D18: Gratis | E18: 0 | F18: 18 | G18: =E18*F18 -> 0
A19: 2 | B19: Vercel (frontend) | C19: Hosting frontend React / Next.js. Plan hobby 100% gratuito. | D19: Gratis | E19: 0 | F19: 18 | G19: =E19*F19 -> 0
A20: 3 | B20: Neon / Supabase (PostgreSQL cloud) | C20: Base de datos PostgreSQL gratuita en nube – 512 MB incluidos. | D20: Gratis | E20: 0 | F20: 18 | G20: =E20*F20 -> 0
A21: 4 | B21: Cloudinary Free | C21: Almacenamiento de fotos de muebles. 25 GB gratis. | D21: Gratis | E21: 0 | F21: 18 | G21: =E21*F21 -> 0
A22: 5 | B22: Brevo / SendGrid Free | C22: Notificaciones automáticas al cliente. 300 emails/día gratis. | D22: Gratis | E22: 0 | F22: 18 | G22: =E22*F22 -> 0
A23: 6 | B23: GitHub Actions (CI/CD) | C23: Automatización de despliegues. 2 000 min/mes gratis. | D23: Gratis | E23: 0 | F23: 18 | G23: =E23*F23 -> 0
A24: SUBTOTAL – Servicios Cloud Gratuitos | G24: =SUM(G18:G23) -> 0
A25: TOTAL SOFTWARE Y SERVICIOS (18 meses) | G25: =G16+G24 -> 0
A26: Nota: Todo el software es open-source / gratuito. Sin licencias comerciales. Costo total = $0.

Sheet 3. Arquitectura Red
A1: FICHA TÉCNICA – ARQUITECTURA DE RED | SIGTRM – La Caqueteña
A2: Arquitectura: Cloud-first (sin servidor local) | Junio 2026
A3: # | B3: Componente | C3: Descripción / Especificación | D3: Costo/mes (COP) | E3: Meses | F3: Costo Total (COP)
A4: A. Conectividad Taller
A5: 1 | B5: Internet banda ancha taller | C5: Plan ~50 Mbps – operador local / ETB / Claro Colombia. Conecta los 3 portátiles. | D5: 65000 | E5: 18 | F5: =D5*E5 -> 1170000
A6: TOTAL RED Y CONECTIVIDAD (18 meses) | F6: =SUM(F5:F5) -> 1170000
A8: DIAGRAMA DE ARQUITECTURA (descripción)
A9: Capa Cliente | B9: Navegador web en los 3 portátiles Lenovo + dispositivos del taller → WiFi Router
A10: Capa Presentación | B10: Frontend React.js → Vercel (CDN global, HTTPS)
A11: Capa Lógica | B11: Backend Node.js + Express → Railway (contenedor Docker)
A12: Capa Datos | B12: PostgreSQL en Neon.tech (cloud) – backups automáticos diarios
A13: Almacenamiento Fotos | B13: Cloudinary Free – imágenes de muebles (25 GB)
A14: Notificaciones | B14: Brevo/SendGrid – correos automáticos al cliente
A15: CI/CD | B15: GitHub Actions → despliegue automático en push a rama main

Sheet 4. Recurso Humano
A1: FICHA TÉCNICA – RECURSO HUMANO | SIGTRM – La Caqueteña
A2: Proyecto: SIGTRM | Duración: 18 meses | Equipo: 3 aprendices SENA | SMMLV 2026: $1.750.905
A3: # | B3: Nombre | C3: Rol en el Proyecto | D3: Modalidad | E3: Apoyo mensual (COP) | F3: Meses | G3: Costo Total (COP) | H3: Base legal
A4: Equipo de Desarrollo – Aprendices SENA Tecnólogo (Etapa Productiva 2026 – Ley 2466/2025)
A5: 1 | B5: Danier F. Herrera C. | C5: Líder de Proyecto / Full-Stack Developer | D5: Contrato aprendizaje SENA | E5: 1750905 | F5: 18 | G5: =E5*F5 -> 31516290 | H5: Ley 2466/2025 – 100% SMMLV etapa productiva
A6: 2 | B6: Eydy Y. Bobadilla C. | C6: Frontend Developer / Diseño UX-UI | D6: Contrato aprendizaje SENA | E6: 1750905 | F6: 18 | G6: =E6*F6 -> 31516290 | H6: Ley 2466/2025 – 100% SMMLV etapa productiva
A7: 3 | B7: Jhoan S. Martínez G. | C7: Backend Developer / Base de Datos | D7: Contrato aprendizaje SENA | E7: 1750905 | F7: 18 | G7: =E7*F7 -> 31516290 | H7: Ley 2466/2025 – 100% SMMLV etapa productiva
A8: TOTAL RECURSO HUMANO (18 meses) | G8: =SUM(G5:G7) -> 94548870
A10: Referencia de remuneración – Aprendices SENA 2026 (Ley 2466 de 2025)
A11: Etapa lectiva (teórica) | B11: 75% del SMMLV | G11: $1.313.179 / mes
A12: Etapa productiva (práctica) | B12: 100% del SMMLV | G12: $1.750.905 / mes ← Valor usado en esta ficha
A13: SMMLV 2026 | B13: Decreto 1469 de 2025 | G13: $1.750.905
A14: Auxilio de transporte 2026 | B14: Decreto 1469 de 2025 | G14: $162.000 (adicional)

Sheet 5. Comparativo Proveedores
A1: ANÁLISIS COMPARATIVO DE PROVEEDORES | SIGTRM – La Caqueteña
A2: Criterios: Costo, Specs, Garantía, Disponibilidad Colombia | Fuente: Ktronix.com – Junio 2026
A4: 1. LAPTOPS DE DESARROLLO – Comparativo 3 modelos (Ktronix.com)
A5: Marca/Modelo | B5: Procesador | C5: RAM | D5: Almacenamiento | E5: Garantía | F5: Precio COP | G5: Disponibilidad | H5: ¿Seleccionado? | I5: Enlace Ktronix
A6: Lenovo IdeaPad 3 15ALC6 | B6: AMD Ryzen 5 5500U | C6: 8 GB DDR4 | D6: SSD 512 GB NVMe | E6: 1 año | F6: 1849900 | G6: Ktronix, Éxito | H6: ✅ SÍ – mejor precio/specs | I6: https://www.ktronix.com/computadores-tablet/computadores-portatiles/c/BI_104_KTRON
A7: ASUS VivoBook 15 | B7: Intel Core i3-1215U | C7: 8 GB DDR4 | D7: SSD 256 GB | E7: 1 año | F7: 1649000 | G7: Ktronix, Falabella | H7: ❌ No – almacenamiento bajo | I7: https://www.ktronix.com/computadores-tablet/computadores-portatiles/c/BI_104_KTRON
A8: HP Laptop 15-fd | B8: Intel Core i5-1235U | C8: 8 GB DDR4 | D8: SSD 512 GB | E8: 1 año | F8: 2199000 | G8: Ktronix, HP Store CO | H8: ❌ No – precio más alto | I8: https://www.ktronix.com/computadores-tablet/computadores-portatiles/c/BI_104_KTRON
A9: → Selección: Lenovo IdeaPad 3 – mejor relación costo/especificación. Ryzen 5 maneja Docker, Node.js y MySQL simultáneamente.
A11: 2. ROUTER WIFI – Comparativo 3 modelos (Ktronix.com)
A12: Marca/Modelo | B12: Estándar | C12: Bandas | D12: Velocidad | E12: Garantía | F12: Precio COP | G12: Disponibilidad | H12: ¿Seleccionado? | I12: Enlace Ktronix
A13: TP-Link TL-WR840N | B13: WiFi 4 (N) | C13: 2.4 GHz | D13: 300 Mbps | E13: 1 año | F13: 79000 | G13: Ktronix | H13: ✅ SÍ – suficiente para 3 PC | I13: https://www.ktronix.com/casa-inteligente-domotica/redes-wifi/c/BI_142_KTRON
A14: TP-Link Archer AX23 | B14: WiFi 6 | C14: Dual band | D14: 1201 Mbps | E14: 1 año | F14: 249000 | G14: Ktronix | H14: ❌ No – sobrepasa necesidad | I14: https://www.ktronix.com/casa-inteligente-domotica/redes-wifi/c/BI_142_KTRON
A15: D-Link DIR-825 | B15: WiFi 5 (AC) | C15: Dual band | D15: 1200 Mbps | E15: 1 año | F15: 159900 | G15: Ktronix | H15: ❌ No – precio mayor por specs | I15: https://www.ktronix.com/casa-inteligente-domotica/redes-wifi/c/BI_142_KTRON
A16: → Selección: TP-Link TL-WR840N – económico, estable y suficiente para el volumen de 3 portátiles + tablets del taller.
A18: 3. UPS / REGULADOR – Comparativo 3 modelos
A19: Marca/Modelo | B19: Capacidad | C19: Tomas | D19: Autonomía | E19: Garantía | F19: Precio COP | G19: Disponibilidad | H19: ¿Seleccionado? | I19: Enlace Ktronix
A20: Forza Power FX-751 | B20: 750 VA / 375 W | C20: 6 tomas | D20: ~10 min PC | E20: 1 año | F20: 189000 | G20: Ktronix, Éxito | H20: ✅ SÍ – precio justo | I20: https://www.ktronix.com/accesorios-electronica/reguladores-voltaje-ups-multitomas/c/BI_146_KTRON
A21: APC BVX700 | B21: 700 VA / 390 W | C21: 6 tomas | D21: ~8 min PC | E21: 2 años | F21: 289000 | G21: Éxito, APC Store | H21: ❌ No – precio mayor | I21: https://www.ktronix.com/accesorios-electronica/reguladores-voltaje-ups-multitomas/c/BI_146_KTRON
A22: Regulador SL 1200 VA | B22: 1200 VA | C22: 8 tomas | D22: Solo regulación | E22: 1 año | F22: 99000 | G22: Ferretería / Éxito | H22: ❌ No – sin batería UPS | I22: https://www.ktronix.com/accesorios-electronica/reguladores-voltaje-ups-multitomas/c/BI_146_KTRON

Sheet 6. Costo Total Proyecto
A1: ESTIMACIÓN DE COSTO TOTAL | SIGTRM – Taller La Caqueteña
A2: Sistema Inteligente de Gestión | Duración: 18 meses | Equipo: 3 aprendices SENA
A3: Categoría | B3: Componente / Descripción | C3: Tipo | D3: Período | E3: Costo (COP)
A4: 1. HARDWARE
A5: Hardware | B5: 3 Laptops Lenovo IdeaPad 3 (Ktronix) + mouse x3 + maletines x3 | C5: CAPEX | D5: Único | E5: ='1. Hardware'!F8 -> 5909700
A6: Hardware | B6: Infraestructura red taller (router, switch, cable UTP, UPS) | C6: CAPEX | D6: Único | E6: ='1. Hardware'!F14 -> 482900
A7: SUBTOTAL HARDWARE | E7: =SUM(E5:E6) -> 6392600
A8: 2. SOFTWARE Y LICENCIAS
A9: Software | B9: Stack open source + cloud gratuito (NetBeans, VS Code, MySQL, GitHub, etc.) | C9: Gratis | D9: 18 meses | E9: ='2. Software'!G25 -> 0
A10: 3. CONECTIVIDAD
A11: Red / Internet | B11: Internet ~50 Mbps – taller ($65.000/mes × 18 meses) | C11: OPEX | D11: 18 meses | E11: ='3. Arquitectura Red'!F6 -> 1170000
A12: 4. RECURSO HUMANO
A13: Recurso Humano | B13: Aprendiz 1 – Líder / Full-Stack (etapa productiva × 18 meses × $1.750.905) | C13: Aprendiz SENA | D13: 18 meses | E13: ='4. Recurso Humano'!G5 -> 31516290
A14: Recurso Humano | B14: Aprendiz 2 – Frontend / UX-UI (etapa productiva × 18 meses × $1.750.905) | C14: Aprendiz SENA | D14: 18 meses | E14: ='4. Recurso Humano'!G6 -> 31516290
A15: Recurso Humano | B15: Aprendiz 3 – Backend / BD (etapa productiva × 18 meses × $1.750.905) | C15: Aprendiz SENA | D15: 18 meses | E15: ='4. Recurso Humano'!G7 -> 31516290
A16: SUBTOTAL RECURSO HUMANO | E16: =SUM(E13:E15) -> 94548870
A18: COSTO TOTAL DEL PROYECTO | E18: =E7+E9+E11+E16 -> 102111470
A20: NOTAS Y SUPUESTOS
A21: • 3 aprendices SENA Tecnólogo Desarrollo de Software en etapa productiva – Ley 2466/2025.
A22: • Apoyo mensual: $1.750.905 (100% SMMLV 2026) por aprendiz × 18 meses.
A23: • Hardware cotizado en Ktronix.com (junio 2026) – precios sujetos a variación.
A24: • Todo el software es gratuito/open-source: $0 en licencias.
A25: • Internet taller: operador local (~$65.000/mes × 18 meses).
A26: • Arquitectura 100% cloud (Railway + Vercel + Neon) – sin costo de servidor físico.
